areavolume/__init__.py
areavolume/formulas.py
Area_and_Volumes-0.2.dist-info/LICENSE
Area_and_Volumes-0.2.dist-info/METADATA
Area_and_Volumes-0.2.dist-info/WHEEL
Area_and_Volumes-0.2.dist-info/top_level.txt
Area_and_Volumes-0.2.dist-info/RECORD
